LICENSE
MANIFEST.in
README.rst
setup.cfg
setup.py
Shahi/Shahi_date.py
Shahi/Shahi_datetime.py
Shahi/__init__.py
Shahi/algorithms.py
Shahi/algorithms_c.c
Shahi/algorithms_pure.py
Shahi/compat.py
Shahi/constants.py
Shahi/helpers.py
Shahi/timezones.py
Shahi.egg-info/PKG-INFO
Shahi.egg-info/SOURCES.txt
Shahi.egg-info/dependency_links.txt
Shahi.egg-info/top_level.txt
Shahi.egg-info/zip-safe
Shahi/formatting/__init__.py
Shahi/formatting/constants.py
Shahi/formatting/formatters.py
Shahi/formatting/directives/__init__.py
Shahi/formatting/directives/ampm.py
Shahi/formatting/directives/base.py
Shahi/formatting/directives/day.py
Shahi/formatting/directives/month.py
Shahi/formatting/directives/persian.py
Shahi/formatting/directives/time.py
Shahi/formatting/directives/tz.py
Shahi/formatting/directives/year.py